powergate/__init__.py
powergate/admin/__init__.py
powergate/admin/v1/__init__.py
powergate/admin/v1/admin_pb2.py
powergate/admin/v1/admin_pb2_grpc.py
powergate/user/__init__.py
powergate/user/v1/__init__.py
powergate/user/v1/user_pb2.py
powergate/user/v1/user_pb2_grpc.py
grpc_powergatec_lient-1.1.1.dist-info/METADATA
grpc_powergatec_lient-1.1.1.dist-info/WHEEL
grpc_powergatec_lient-1.1.1.dist-info/top_level.txt
grpc_powergatec_lient-1.1.1.dist-info/RECORD
