Metadata-Version: 2.1
Name: grpc-powergatec-lient
Version: 1.1.1
Summary: UNKNOWN
Home-page: https://github.com/textileio/powergate
Author: Textile
Author-email: contact@textile.io
License: UNKNOWN
Platform: UNKNOWN
Requires-Dist: protobuf
Requires-Dist: grpcio
